{"total":4,"rows":[{"accounts":"","approveend":"","approveendtxt":"","approvegoto":"1","approveidea1":"","approveidea2":"","approveidea3":"","approvemoney":"222","approveperson1":"rrr","approveperson2":"","approveperson3":"","approveresult1":"1","approveresult1txt":"同意","approveresult2":"","approveresult2txt":"","approveresult3":"","approveresult3txt":"","aprrovedate1":"2014-12-21","aprrovedate2":"","aprrovedate3":"","body0":"患病","body1":"健康","body2":"健康","body3":"","body4":"","createtime":"2014-12-21 14:33:20.0","f_familyid":"237999","f_income":"2250","familyid":"237999","familyno":"22020106050495","famsort":"失业","fde":"F","fdefamilyno":"0","fdename":"","fm_sex":"男","fmage":"45","jd":"延江街道","masterid":"928337","mastername":"于晓光","on_no":"2202010605","onallname":"吉林省吉林市昌邑区延江街道铁江社区","operstate":"普通户","paperid":"22020219690417273X","percount":"3","qx":"昌邑区","rel0":"本人","rel1":"父女","rel2":"配偶","rel3":"","rel4":"","res0":"非农户口","res1":"非农户口","res2":"非农户口","res3":"","res4":"","salcount":"3","serialno":"7f23f173-9ced-4388-952d-a935bbcf7d50","sfzh_jtcy0":"22020219690417273X","sfzh_jtcy1":"220202199710194221","sfzh_jtcy2":"220204197003222426","sfzh_jtcy3":"","sfzh_jtcy4":"","sq":"铁江社区","tjzId":"41","updatetime":"2014-12-21 14:33:20.0","xm_jtcy0":"于晓光","xm_jtcy1":"于渌葳","xm_jtcy2":"张秀艳","xm_jtcy3":"","xm_jtcy4":""},{"accounts":"","approveend":"","approveendtxt":"","approvegoto":"2","approveidea1":"","approveidea2":"","approveidea3":"","approvemoney":"666","approveperson1":"888","approveperson2":"rrrr","approveperson3":"","approveresult1":"1","approveresult1txt":"同意","approveresult2":"1","approveresult2txt":"同意","approveresult3":"","approveresult3txt":"","aprrovedate1":"2014-12-21","aprrovedate2":"2014-12-21","aprrovedate3":"","body0":"健康","body1":"健康","body2":"健康","body3":"","body4":"","createtime":"2014-12-21 14:34:21.0","f_familyid":"238003","f_income":"1150","familyid":"238003","familyno":"22020110010494","famsort":"其它","fde":"F","fdefamilyno":"0","fdename":"","fm_sex":"男","fmage":"44","jd":"文庙街道","masterid":"928353","mastername":"李强","on_no":"2202011001","onallname":"吉林省吉林市昌邑区文庙街道天胜社区","operstate":"普通户","paperid":"220202197007173032","percount":"3","qx":"昌邑区","rel0":"本人","rel1":"父子","rel2":"配偶","rel3":"","rel4":"","res0":"非农户口","res1":"非农户口","res2":"非农户口","res3":"","res4":"","salcount":"3","serialno":"156ceb5b-7e9b-4bba-af30-0b4841caaaa5","sfzh_jtcy0":"220202197007173032","sfzh_jtcy1":"220211199508114212","sfzh_jtcy2":"220204197007010324","sfzh_jtcy3":"","sfzh_jtcy4":"","sq":"天胜社区","tjzId":"42","updatetime":"2014-12-21 14:38:24.0","xm_jtcy0":"李强","xm_jtcy1":"李奉桐","xm_jtcy2":"徐丽红","xm_jtcy3":"","xm_jtcy4":""},{"accounts":"","approveend":"1","approveendtxt":"同意救助","approvegoto":"3","approveidea1":"","approveidea2":"","approveidea3":"","approvemoney":"666","approveperson1":"4455","approveperson2":"顶顶顶","approveperson3":"掌声呢","approveresult1":"1","approveresult1txt":"同意","approveresult2":"1","approveresult2txt":"同意","approveresult3":"1","approveresult3txt":"同意","aprrovedate1":"2014-12-18","aprrovedate2":"2014-12-19","aprrovedate3":"2014-12-20","body0":"健康","body1":"健康","body2":"健康","body3":"健康","body4":"","createtime":"2014-12-18 15:42:09.0","f_familyid":"238020","f_income":"3000","familyid":"238020","familyno":"22020104070884","famsort":"失业","fde":"F","fdefamilyno":"0","fdename":"","fm_sex":"男","fmage":"43","jd":"东局子街道","masterid":"928436","mastername":"韩宇辉","on_no":"2202010407","onallname":"吉林省吉林市昌邑区东局子街道盛昌社区","operstate":"普通户","paperid":"220204197107223618","percount":"4","qx":"昌邑区","rel0":"本人","rel1":"父女","rel2":"母女","rel3":"兄弟","rel4":"","res0":"非农户口","res1":"非农户口","res2":"非农户口","res3":"非农户口","res4":"","salcount":"4","serialno":"ac68bc97-cde2-4842-aecf-0885ad6a8670","sfzh_jtcy0":"220204197107223618","sfzh_jtcy1":"220204199506130629","sfzh_jtcy2":"220204200108170620","sfzh_jtcy3":"22020419740308363X","sfzh_jtcy4":"","sq":"盛昌社区","tjzId":"28","updatetime":"2014-12-20 08:57:39.0","xm_jtcy0":"韩宇辉","xm_jtcy1":"韩佳邑","xm_jtcy2":"韩天意","xm_jtcy3":"韩宇龙","xm_jtcy4":""},{"accounts":"205528311100054","approveend":"","approveendtxt":"","approvegoto":"1","approveidea1":"","approveidea2":"","approveidea3":"","approvemoney":"333","approveperson1":"444","approveperson2":"","approveperson3":"","approveresult1":"1","approveresult1txt":"同意","approveresult2":"","approveresult2txt":"","approveresult3":"","approveresult3txt":"","aprrovedate1":"2014-12-18","aprrovedate2":"","aprrovedate3":"","body0":"患病","body1":"","body2":"","body3":"","body4":"","createtime":"2014-12-18 15:54:17.0","f_familyid":"240913","f_income":"70","familyid":"240913","familyno":"22020203040769","famsort":"无业","fde":"F","fdefamilyno":"0","fdename":"","fm_sex":"男","fmage":"58","jd":"向阳街道","masterid":"981991","mastername":"马治","on_no":"2202020304","onallname":"吉林省吉林市船营区向阳街道北安社区","operstate":"在保户","paperid":"220204195608081815","percount":"1","qx":"船营区","rel0":"本人","rel1":"","rel2":"","rel3":"","rel4":"","res0":"非农户口","res1":"","res2":"","res3":"","res4":"","salcount":"1","serialno":"eeb35d0d-4860-42ac-b47f-b35ede0ca580","sfzh_jtcy0":"220204195608081815","sfzh_jtcy1":"","sfzh_jtcy2":"","sfzh_jtcy3":"","sfzh_jtcy4":"","sq":"北安社区","tjzId":"29","updatetime":"","xm_jtcy0":"马治","xm_jtcy1":"","xm_jtcy2":"","xm_jtcy3":"","xm_jtcy4":""}]}